dnikit_tensorflow/__init__.py
dnikit_tensorflow/_sample_datasets.py
dnikit_tensorflow/_sample_models.py
dnikit_tensorflow/py.typed
dnikit_tensorflow/_tensorflow/__init__.py
dnikit_tensorflow/_tensorflow/_tensorflow_file_loaders.py
dnikit_tensorflow/_tensorflow/_tensorflow_loading.py
dnikit_tensorflow/_tensorflow/_tensorflow_protocols.py
dnikit_tensorflow/_tensorflow/_tf1_file_loaders.py
dnikit_tensorflow/_tensorflow/_tf1_loading.py
dnikit_tensorflow/_tensorflow/_tf1_model.py
dnikit_tensorflow/_tensorflow/_tf2_file_loaders.py
dnikit_tensorflow/_tensorflow/_tf2_loading.py
dnikit_tensorflow/_tensorflow/_tf2_model.py
dnikit_tensorflow/samples/__init__.py
dnikit_tensorflow/samples/_simple_cnn_keras.py
dnikit_tensorflow/samples/_simple_lstm_tensorflow.py
dnikit_tensorflow-2.0.0.dist-info/WHEEL
dnikit_tensorflow-2.0.0.dist-info/METADATA
dnikit_tensorflow-2.0.0.dist-info/RECORD
